[{"ID":"11063","NameOfCourse":"אנגלית בסיסי"},{"ID":"11064","NameOfCourse":"אנגלית מתקדמים א'"},{"ID":"11179","NameOfCourse":"מבוא לפיזיקה אקדמית"},{"ID":"11947","NameOfCourse":"מיומנות למידה"},{"ID":"11004","NameOfCourse":"חדווא 1מ"},{"ID":"11002","NameOfCourse":"אלגברה 1מח"},{"ID":"61740","NameOfCourse":"מערכות ספרתיות"},{"ID":"61741","NameOfCourse":"מבוא למדעי המחשב"},{"ID":"11351","NameOfCourse":"אוריינות בעברית"},{"ID":"11006","NameOfCourse":"חדווא 2מ"},{"ID":"11020","NameOfCourse":"אלגברה 2מח"},{"ID":"11060","NameOfCourse":"אנגלית מתקדמים ב'"},{"ID":"61743","NameOfCourse":"מתמטיקה דיסקרטית 1"},{"ID":"61744","NameOfCourse":"ארגון ותכנון המחשב"},{"ID":"61745","NameOfCourse":"מבוא לתכנות מערכות"},{"ID":"11129","NameOfCourse":"טורים,התמרות ומשוואת דיפרנציאליות"},{"ID":"61746","NameOfCourse":"לוגיקה"},{"ID":"61747","NameOfCourse":"מבני נתונים"},{"ID":"61748","NameOfCourse":"ארכיטקטורה ומבנה המחשב"},{"ID":"61749","NameOfCourse":"מתמתיקה דיסקרטית 2"},{"ID":"61750","NameOfCourse":"מבוא להנדסת תוכנה"},{"ID":"11158","NameOfCourse":"מכניקה להנדסת תוכנה"},{"ID":"61751","NameOfCourse":"תכנות מונחה עצמים"},{"ID":"61752","NameOfCourse":"מערכות הפעלה"},{"ID":"61753","NameOfCourse":"אלגורתמים"},{"ID":"61755","NameOfCourse":"מערכות מסדי נתונים מ"},{"ID":"11069","NameOfCourse":"אנגלית טכנית יישומית - תכנה"},{"ID":"61756","NameOfCourse":"שיטות הנדסיות לפיתוח תכנה"},{"ID":"61757","NameOfCourse":"מבוא לבדיקות תוכנה"},{"ID":"61759","NameOfCourse":"אוטומטים וחישוביות"},{"ID":"61760","NameOfCourse":"הסתברות להנדסת תוכנה"},{"ID":"61769","NameOfCourse":"ממשק אדם מחשב"},{"ID":"11159","NameOfCourse":"חשמל ומגנטיות להנדסת תכנה"},{"ID":"61758","NameOfCourse":"מבנה מערכות הפעלה וזמן אמת"},{"ID":"61761","NameOfCourse":"כריית נתונים ומערכות לומדות"},{"ID":"61763","NameOfCourse":"תורת הקומפלציה"},{"ID":"61764","NameOfCourse":"גרפיקה ממוחשבת"},{"ID":"61765","NameOfCourse":"רשתות מחשבים"},{"ID":"61766","NameOfCourse":"פרויקט בהנדסת תכנה שלב א'"},{"ID":"61767","NameOfCourse":"אבטחת מידע וקריפטולוגיה"},{"ID":"61768","NameOfCourse":"תכנות מקבילי ומבוזר וטכנולוגית ענן"},{"ID":"61770","NameOfCourse":"ממשק אדם מחשב מ'"},{"ID":"61765","NameOfCourse":"פרויקט בהנדסת תכנה שלב ב'"},{"ID":"11198","NameOfCourse":"פיזיקה מודרנית"},{"ID":"41942","NameOfCourse":"מבוא לביולוגיה מולקולרית"},{"ID":"61957","NameOfCourse":"תורת המשחקים"},{"ID":"61958","NameOfCourse":"תורת המידע"},{"ID":"61989","NameOfCourse":"מחשבים קוונטים"},{"ID":"61991","NameOfCourse":"תכנות מדעי"},{"ID":"61992","NameOfCourse":"מבוא לחישה ולמידה"},{"ID":"61959","NameOfCourse":"אנליזה נומרית"},{"ID":"61960","NameOfCourse":"מבוא לאופטמיזציה"},{"ID":"61961","NameOfCourse":"אחזור מידע"},{"ID":"61962","NameOfCourse":"גיאומטריה חישובית ומידול"},{"ID":"61963","NameOfCourse":"בינה מלאכותית"},{"ID":"61964","NameOfCourse":"ויזואליזציה של המידע"},{"ID":"61965","NameOfCourse":"ניתוח של נתונתי הרשתות"},{"ID":"61966","NameOfCourse":"סמינר מערכות לומדות"},{"ID":"61967","NameOfCourse":"סמינר באלגוריתמים אקראיים"},{"ID":"61968","NameOfCourse":"סמינר באלגורתמים מתקדמים"},{"ID":"61969","NameOfCourse":"סמינר באימות תכנה"},{"ID":"61970","NameOfCourse":"סמינר באוטומטים"},{"ID":"61971","NameOfCourse":"עיבוד תמונה ספרתי"},{"ID":"61972","NameOfCourse":"עיבוד אותות ספרתי DSP"},{"ID":"61973","NameOfCourse":"תקשורת אלחוטית ורשתות מחשבים"},{"ID":"61974","NameOfCourse":"בדיקת מערכות ספרתיות"},{"ID":"61975","NameOfCourse":"דחיסת נתונים"},{"ID":"61976","NameOfCourse":"ביולוגיה חישובית"},{"ID":"61994","NameOfCourse":"ראיית מכונה"},{"ID":"61834","NameOfCourse":"מסדי נתונים מבוזרים"},{"ID":"61977","NameOfCourse":"טכנולוגיית WEB מתקדם"},{"ID":"61978","NameOfCourse":"אימות תכנה וחומרה"},{"ID":"61979","NameOfCourse":"מחשוב ענן"},{"ID":"61980","NameOfCourse":"שפות תכנות"},{"ID":"61981","NameOfCourse":"הנדסת דרישות"},{"ID":"61982","NameOfCourse":"מעבדה במידול מערכות אקולוגיות"},{"ID":"61983","NameOfCourse":"מעבדה בתכנות מקבילי והטרוגני"},{"ID":"61984","NameOfCourse":"מעבדה באופטימיזיציה"},{"ID":"61985","NameOfCourse":"מעבדה בפיתוח יישמים באנדרואיד"},{"ID":"61986","NameOfCourse":"מעבדה בסחר אלקטורני"},{"ID":"61987","NameOfCourse":"מעבדה בכריית נתונים"},{"ID":"61988","NameOfCourse":"מעבדה בעיצוב תבניות בתכנה"},{"ID":"61990","NameOfCourse":"מעבדה בטכנולוגיות תכנות צד לקוח ושרת"}]